random_ua/__init__.py
random_ua/random_ua.py
ramdom_ua-1.0.dist-info/LICENSE
ramdom_ua-1.0.dist-info/METADATA
ramdom_ua-1.0.dist-info/WHEEL
ramdom_ua-1.0.dist-info/top_level.txt
ramdom_ua-1.0.dist-info/RECORD
