Metadata-Version: 2.1
Name: ramdom-ua
Version: 1.0
Summary: get ua
Home-page: https://gitee.com/liyufeng0202/random_ua
Author: liyf
Author-email: liyufeng_0202@163.com
License: UNKNOWN
Platform: UNKNOWN
Classifier: Programming Language :: Python :: 3
Classifier: License :: OSI Approved :: MIT License
Classifier: Operating System :: OS Independent
